{
 "title"   : "A fierce young lion with gloomy red eyes",
 "og_image": "lion.png",
 "entries" : [
  { "image": "nolde_flyers.jpg",
    "text" : "I attended an exhibition by Emil Nolde recently and brought home these flyers. Since I did collages from art flyers before, I asked my <a href='https://www.facebook.com/photo.php?fbid=212632802435753' target=_blank>friends on Facebook</a> what to do with these. 'A fierce young lion with gloomy red eyes' got the most upvotes." },
  { "image": "lion_workbench.jpg",
    "text" : "So here it is, a fierce young lion with gloomy red eyes made with the colors of Emil Nolde." }
 ]
}
